README.rst
setup.py
openexchangerates/__init__.py
openexchangerates/exchange.py
python_openexchangerates.egg-info/PKG-INFO
python_openexchangerates.egg-info/SOURCES.txt
python_openexchangerates.egg-info/dependency_links.txt
python_openexchangerates.egg-info/requires.txt
python_openexchangerates.egg-info/top_level.txt