Metadata-Version: 1.1
Name: python-openexchangerates
Version: 0.1.0
Summary: Open exchange rates
Home-page: http://python-bitcoinopenexchange.readthedocs.org/en/latest/
Author: Yeison Cardona
Author-email: yeison.eng@gmail.com
License: BSD 3-Clause
Download-URL: https://bitbucket.org/yeisoneng/python-openexchangerates/src
Platform: UNKNOWN
